obt.py
setup.cfg
setup.py
obt.egg-info/PKG-INFO
obt.egg-info/SOURCES.txt
obt.egg-info/dependency_links.txt
obt.egg-info/entry_points.txt
obt.egg-info/requires.txt
obt.egg-info/top_level.txt