Metadata-Version: 1.1
Name: obt
Version: 0.1.0
Summary: A Python library for The Oslo-Bergen Tagger
Home-page: https://github.com/draperunner/obt
Author: Mats Byrkjeland
Author-email: matsbyr@gmail.com
License: MIT
Keywords: pos-tagging nlp pos
Platform: UNKNOWN
Classifier: Development Status :: 4 - Beta
Classifier: Intended Audience :: Developers
Classifier: Topic :: Scientific/Engineering :: Artificial Intelligence
Classifier: License :: OSI Approved :: MIT License
Classifier: Programming Language :: Python :: 3
Classifier: Programming Language :: Python :: 3.3
Classifier: Programming Language :: Python :: 3.4
Classifier: Programming Language :: Python :: 3.5
